onion_clustering/__init__.py
onion_clustering/classes.py
onion_clustering/first_classes.py
onion_clustering/functions.py
onion_clustering/main.py
onion_clustering/main_2d.py
onion_clustering/utilities.py
onion_clustering-0.2.5.dist-info/LICENSE
onion_clustering-0.2.5.dist-info/METADATA
onion_clustering-0.2.5.dist-info/WHEEL
onion_clustering-0.2.5.dist-info/top_level.txt
onion_clustering-0.2.5.dist-info/RECORD
