Metadata-Version: 2.1
Name: onion_clustering
Version: 0.2.5
Summary: Code for unsupervised clustering of time-correlated data.
Maintainer-email: Matteo Becchi <bechmath@gmail.com>
Project-URL: github, https://github.com/matteobecchi/timeseries_analysis/
Requires-Python: <3.11,>=3.9
License-File: LICENSE
Requires-Dist: matplotlib
Requires-Dist: numpy
Requires-Dist: plotly
Requires-Dist: scipy
